Metadata-Version: 2.1
Name: krishto
Version: 0.2
Summary: Python code Encryption and Decryption use algorithms
Home-page: UNKNOWN
Author: K.A.ISHAN OSHADA
Author-email: <ic31908@gmail.com>
License: UNKNOWN
Keywords: krishto.Encryption_methods,krishto.Encryption_methods().E2D_1,etc..
Platform: UNKNOWN
Classifier: Development Status :: 1 - Planning
Classifier: Intended Audience :: Developers
Classifier: Programming Language :: Python :: 3
Classifier: Operating System :: Unix
Classifier: Operating System :: MacOS :: MacOS X
Classifier: Operating System :: Microsoft :: Windows
